py_thai_num/__init__.py
py_thai_num/py_thai_num/__init__.py
py_thai_num/py_thai_num/file_thai_num.py
py_thai_num/py_thai_num/py_thai_num.py
py_thai_num-0.2.1.dist-info/METADATA
py_thai_num-0.2.1.dist-info/WHEEL
py_thai_num-0.2.1.dist-info/top_level.txt
py_thai_num-0.2.1.dist-info/RECORD
