Metadata-Version: 2.1
Name: py-thai-num
Version: 0.2.1
Summary: python lib for conversion Thai numerical to global numerical.
Home-page: https://github.com/worakrit-sittirit/py_thai_num.git
Author: Worakrit Sittirit
Author-email: kritsitti.coe@gmail.com
License: MIT
Project-URL: Source Code, https://github.com/worakrit-sittirit/py_thai_num
Keywords: Thai number to eng
